Core/__init__.py
gui/__init__.py
hybrides/__init__.py
serve/__init__.py
oscliantivirus-0.0.1.dist-info/METADATA
oscliantivirus-0.0.1.dist-info/WHEEL
oscliantivirus-0.0.1.dist-info/entry_points.txt
oscliantivirus-0.0.1.dist-info/top_level.txt
oscliantivirus-0.0.1.dist-info/RECORD
