Metadata-Version: 2.1
Name: oscliantivirus
Version: 0.0.1
Summary: 🛡️🛠️ "oscliantivirus" is an advanced antivirus package designed for both developers and standard users to provide custom security features for their systems.
Home-page: https://github.com/yourusername/oscliantivirus
Author: Juste Elysée MALNADILA
Author-email: malandilajusteelysee@gmail.com
Classifier: Development Status :: 3 - Alpha
Classifier: License :: OSI Approved :: MIT License
Classifier: Programming Language :: Python :: 3
Classifier: Programming Language :: Python :: 3.8
Classifier: Programming Language :: Python :: 3.9
Classifier: Programming Language :: Python :: 3.10
Classifier: Programming Language :: Python :: Implementation :: CPython
Classifier: Programming Language :: Python :: Implementation :: PyPy
Requires-Python: >=3.8
